aospy/__init__.py
aospy/client/__init__.py
aospy/client/apispec.py
aospy/client/apispec_operids.py
aospy/client/client.py
aospy/client/utils.py
aospy/swagger/__init__.py
aospy/swagger/client.py
aospy/swagger/indexer.py
aospy/swagger/groups/__init__.py
aospy/swagger/groups/blueprints.py
aospy/swagger/groups/devices.py
aospy/swagger/groups/hcls.py
aospy/swagger/groups/packages.py
aospy/swagger/groups/system_agents.py
aospy/swagger/groups/system_services.py
aospy/swagger/groups/templates.py
apstra_aospy_swagger-0.5.0.dist-info/DESCRIPTION.rst
apstra_aospy_swagger-0.5.0.dist-info/METADATA
apstra_aospy_swagger-0.5.0.dist-info/RECORD
apstra_aospy_swagger-0.5.0.dist-info/WHEEL
apstra_aospy_swagger-0.5.0.dist-info/metadata.json
apstra_aospy_swagger-0.5.0.dist-info/top_level.txt
