Metadata-Version: 2.0
Name: apstra-aospy-swagger
Version: 0.5.0
Summary: Python Swagger client for AOS Server
Home-page: http://www.apstra.com
Author: Apstra, Inc.
Author-email: support@apstra.com
License: Apache 2.0
Platform: UNKNOWN
Requires-Dist: bidict
Requires-Dist: cached-property
Requires-Dist: first
Requires-Dist: halutz (>=0.4.2)
Requires-Dist: inflection
Requires-Dist: requests
Requires-Dist: retrying
Requires-Dist: six
